{"formautofill@mozilla.org":{"permissions":["internal:svgContextPropertiesAllowed","internal:privateBrowsingAllowed"],"origins":[]},"pictureinpicture@mozilla.org":{"permissions":["internal:svgContextPropertiesAllowed","internal:privateBrowsingAllowed"],"origins":[]},"screenshots@mozilla.org":{"permissions":["internal:svgContextPropertiesAllowed","internal:privateBrowsingAllowed"],"origins":[]},"webcompat@mozilla.org":{"permissions":["internal:svgContextPropertiesAllowed","internal:privateBrowsingAllowed"],"origins":[]},"default-theme@mozilla.org":{"permissions":["internal:svgContextPropertiesAllowed"],"origins":[]},"addons-search-detection@mozilla.com":{"permissions":["internal:svgContextPropertiesAllowed","internal:privateBrowsingAllowed"],"origins":[]},"google@search.mozilla.org":{"permissions":["internal:svgContextPropertiesAllowed","internal:privateBrowsingAllowed"],"origins":[]},"wikipedia@search.mozilla.org":{"permissions":["internal:svgContextPropertiesAllowed","internal:privateBrowsingAllowed"],"origins":[]},"bing@search.mozilla.org":{"permissions":["internal:svgContextPropertiesAllowed","internal:privateBrowsingAllowed"],"origins":[]},"ddg@search.mozilla.org":{"permissions":["internal:svgContextPropertiesAllowed","internal:privateBrowsingAllowed"],"origins":[]},"amazon@search.mozilla.org":{"permissions":["internal:svgContextPropertiesAllowed","internal:privateBrowsingAllowed"],"origins":[]},"dreamer-bold-colorway@mozilla.org":{"permissions":["internal:privateBrowsingAllowed"],"origins":[]},"panorama-tab-groups@example.com":{"permissions":["internal:privateBrowsingAllowed"],"origins":[]},"uBlock0@raymondhill.net":{"permissions":["internal:privateBrowsingAllowed"],"origins":[]},"side-view@mozilla.org":{"permissions":["internal:svgContextPropertiesAllowed"],"origins":[]},"newtaboverride@agenedia.com":{"permissions":["internal:privateBrowsingAllowed"],"origins":[]},"noise@bootleq":{"permissions":["internal:privateBrowsingAllowed","webNavigation","webRequest"],"origins":[]},"{82b57c0f-7165-4ce2-afe0-f03c11d1fc51}":{"permissions":["internal:privateBrowsingAllowed"],"origins":[]},"doh-rollout@mozilla.org":{"permissions":["internal:svgContextPropertiesAllowed","internal:privateBrowsingAllowed"],"origins":[]}}